wait_for_message/__init__.py
wait_for_message/cli.py
wait_for_message-0.1.8.dist-info/METADATA
wait_for_message-0.1.8.dist-info/WHEEL
wait_for_message-0.1.8.dist-info/entry_points.txt
wait_for_message-0.1.8.dist-info/namespace_packages.txt
wait_for_message-0.1.8.dist-info/top_level.txt
wait_for_message-0.1.8.dist-info/zip-safe
wait_for_message-0.1.8.dist-info/RECORD
