Metadata-Version: 2.1
Name: wait-for-message
Version: 0.1.8
Summary: A simple client server utility that blocks until a message is received on a TCP/IP socket connection
Home-page: https://github.com/soda480/wait-for-message
Author: Emilio Reyes
Author-email: soda480@gmail.com
Maintainer: 
Maintainer-email: 
License: Apache License, Version 2.0
Classifier: Programming Language :: Python
Classifier: Programming Language :: Python :: 3.8
Classifier: Programming Language :: Python :: 3.9
Classifier: Programming Language :: Python :: 3.10
Classifier: Programming Language :: Python :: 3.11
Classifier: Programming Language :: Python :: 3.12
